pyradiance-1.2.0.dist-info/WHEEL
pyradiance-1.2.0.dist-info/METADATA
pyradiance-1.2.0.dist-info/RECORD
pyradiance/rad_params.cpython-313-x86_64-linux-gnu.so
pyradiance/bsdf.cpython-313-x86_64-linux-gnu.so
pyradiance/rt.py
pyradiance/px.py
pyradiance/cv.py
pyradiance/util.py
pyradiance/anci.py
pyradiance/radiance_ext.cpython-313-x86_64-linux-gnu.so
pyradiance/ot.py
pyradiance/genbsdf.py
pyradiance/cal.py
pyradiance/model.py
pyradiance/gen.py
pyradiance/__init__.py
pyradiance/lib/sun.cal
pyradiance/lib/root.cal
pyradiance/lib/ambient1.fmt
pyradiance/lib/LaFortune1.cal
pyradiance/lib/rgb.cal
pyradiance/lib/testimg.cal
pyradiance/lib/tilt.cal
pyradiance/lib/surf.cal
pyradiance/lib/lumdist.cal
pyradiance/lib/rayinit.cal
pyradiance/lib/tregsamp.dat
pyradiance/lib/log3G10.cal
pyradiance/lib/glaze1.cal
pyradiance/lib/norm.cal
pyradiance/lib/ambpos.cal
pyradiance/lib/WINDOW6BSDFt.xml
pyradiance/lib/WGMDiso.cal
pyradiance/lib/perezlum_c.cal
pyradiance/lib/xyz_srgb.cal
pyradiance/lib/noise3.cal
pyradiance/lib/pq.cal
pyradiance/lib/gauss.cal
pyradiance/lib/source.cal
pyradiance/lib/blinds.cal
pyradiance/lib/patch3w.cal
pyradiance/lib/illum.cal
pyradiance/lib/klems_half.cal
pyradiance/lib/cielab.cal
pyradiance/lib/WalterBSDF.cal
pyradiance/lib/normcomp.cal
pyradiance/lib/spharm.cal
pyradiance/lib/LaFortune.cal
pyradiance/lib/trix.dat
pyradiance/lib/rambpos.cal
pyradiance/lib/veil.cal
pyradiance/lib/tumblin.cal
pyradiance/lib/hsv_rgb.cal
pyradiance/lib/peerless.cal
pyradiance/lib/rskysrc.cal
pyradiance/lib/triz.dat
pyradiance/lib/cieluv.cal
pyradiance/lib/genSH.cal
pyradiance/lib/trans2.cal
pyradiance/lib/picdiff.cal
pyradiance/lib/skyfact.cal
pyradiance/lib/vwplanis.cal
pyradiance/lib/fisheye_corr.cal
pyradiance/lib/triy.dat
pyradiance/lib/gaussian.cal
pyradiance/lib/suncal.fmt
pyradiance/lib/noise2.cal
pyradiance/lib/skybright.cal
pyradiance/lib/klems_full.cal
pyradiance/lib/blackbody.cal
pyradiance/lib/cri.cal
pyradiance/lib/glaze2.cal
pyradiance/lib/glass3.cal
pyradiance/lib/reinhartb.cal
