Metadata-Version: 2.1
Name: pyradiance
Version: 1.2.0
Summary: Python inteface for Radiance
Author-Email: Taoning Wang <taoningwang@lbl.gov>
Classifier: License :: OSI Approved :: BSD License
Project-URL: Homepage, https://github.com/lbnl-eta/pyradiance
Requires-Python: >=3.10
Requires-Dist: numpy>=1.2.6
